tailscale_api/__init__.py
tailscale_api/models.py
tailscale_api-2025.1.dist-info/WHEEL
tailscale_api-2025.1.dist-info/METADATA
tailscale_api-2025.1.dist-info/RECORD
