Metadata-Version: 2.4
Name: tailscale-api
Version: 2025.1
Summary: Tools for working with the Tailscale API
License-Expression: MIT
Requires-Dist: httpx>=0.28.1
Requires-Python: >=3.13
Project-URL: Homepage, https://github.com/williamjacksn/tailscale-api
Project-URL: Issues, https://github.com/williamjacksn/tailscale-api/issues
